console_window/ConsoleWindow.py
console_window/__init__.py
console_window-1.4.3.dist-info/licenses/LICENSE
console_window-1.4.3.dist-info/WHEEL
console_window-1.4.3.dist-info/METADATA
console_window-1.4.3.dist-info/RECORD
