Metadata-Version: 2.4
Name: console-window
Version: 1.4.3
Summary: A robust curses wrapper for creating Text User Interfaces (TUIs).
Author-email: Joe Defen <joedef@duck.com>
Requires-Python: >=3.8
Classifier: Development Status :: 3 - Alpha
Classifier: Programming Language :: Python :: 3
Classifier: License :: OSI Approved :: MIT License
Classifier: Operating System :: POSIX :: Linux
Classifier: Topic :: Terminals
Classifier: Topic :: Software Development :: User Interfaces
License-File: LICENSE
